packageshareque/__init__.py
packageshareque-0.2.dist-info/Licence.txt
packageshareque-0.2.dist-info/METADATA
packageshareque-0.2.dist-info/WHEEL
packageshareque-0.2.dist-info/top_level.txt
packageshareque-0.2.dist-info/RECORD
