Metadata-Version: 2.1
Name: packageshareque
Version: 0.2
Summary: Shareque vision2 Library
Author: shareque
License-File: Licence.txt
